amlctor/__init__.py
amlctor/__main__.py
amlctor/amlctor.py
amlctor/core.py
amlctor/exceptions.py
amlctor/input.py
amlctor/schemas.py
amlctor/utils.py
amlctor/apply/__init__.py
amlctor/apply/apply.py
amlctor/confs/__init__.py
amlctor/confs/configs.py
amlctor/denv/__init__.py
amlctor/denv/denv.py
amlctor/denv/dot_env_loader.py
amlctor/init/__init__.py
amlctor/init/args_handling.py
amlctor/init/init.py
amlctor/init/init_structure.py
amlctor/rename/__init__.py
amlctor/rename/rename.py
amlctor/run/__init__.py
amlctor/run/run.py
amlctor/src/__init__.py
amlctor/src/templates/apply/aml
amlctor/src/templates/apply/data_loaders
amlctor/src/templates/init/conda_dependencies
amlctor/src/templates/init/dot_amlignore
amlctor/src/templates/init/dot_env
amlctor/src/templates/init/env_vars
amlctor/src/templates/init/settings
amlctor/tests/__init__.py
amlctor/tests/apply/__init__.py
amlctor/tests/apply/test_apply_path.py
amlctor/tests/core/__init__.py
amlctor/tests/init/__init__.py
amlctor/tests/init/test_env_bank.py
amlctor/tests/run/__init__.py
amlctor/tests/src/templates/settings
amlctor/update/__init__.py
amlctor/update/update.py
amlctor-0.0.2.dist-info/LICENSE
amlctor-0.0.2.dist-info/WHEEL
amlctor-0.0.2.dist-info/METADATA
amlctor-0.0.2.dist-info/RECORD
