Metadata-Version: 2.1
Name: amlctor
Version: 0.0.2
Summary: AML Pipeline Constructor 
Keywords: azure,machine leaning,aml,pipeline
Author-email: Aziz Nadirov <aziznadirov@yahoo.com>
Requires-Python: >=3.9,<3.11
Classifier: License :: OSI Approved :: MIT License
Classifier: Development Status :: 4 - Beta
Classifier: Intended Audience :: Developers
Classifier: Operating System :: OS Independent
Requires-Dist: azureml-core >=1.49.0
Requires-Dist: azureml-pipeline >=1.49.0
Requires-Dist: python-dotenv >=1.0.0
Requires-Dist: pandas >=1.5.3
Requires-Dist: pyarrow >=9.0.0
Requires-Dist: pydantic >=1.10.5
Requires-Dist: Jinja2 >=3.1.2
Project-URL: Source, https://github.com/AzizNadirov/amlctor
